clovers_sarof/__init__.py
clovers_sarof/core/__init__.py
clovers_sarof/core/_clovers.py
clovers_sarof/core/_config.py
clovers_sarof/core/_manager.py
clovers_sarof/core/account.py
clovers_sarof/core/linecard.py
clovers_sarof/core/props_library.json
clovers_sarof/core/tools.py
clovers_sarof-0.1.0.dist-info/METADATA
clovers_sarof-0.1.0.dist-info/WHEEL
clovers_sarof-0.1.0.dist-info/RECORD
