Metadata-Version: 2.3
Name: clovers_sarof
Version: 0.1.0
Summary: 
Author: KarisAya
Author-email: karisaya@foxmail.com
Requires-Python: >=3.12,<4.0
Classifier: Programming Language :: Python :: 3
Classifier: Programming Language :: Python :: 3.12
Classifier: Programming Language :: Python :: 3.13
Requires-Dist: clovers (>=0.4.6,<0.5.0)
Requires-Dist: httpx (>=0.28.1,<0.29.0)
Requires-Dist: linecard (>=0.2.0,<0.3.0)
Requires-Dist: matplotlib (>=3.10.0,<4.0.0)
Requires-Dist: mplfinance (>=0.12.10b0,<0.13.0)
Requires-Dist: pydantic (>=2.10.6,<3.0.0)
Requires-Dist: sqlmodel (>=0.0.24,<0.0.25)
